{
  "nom": "Dupont",
  "prenom": "Jean",
  "poste": "Développeur Python Senior",
  "competences": ["Python", "Django", "Flask", "REST API", "React", "TypeScript"],
  "logiciels": ["Git", "Docker", "VS Code", "PyCharm", "AWS", "PostgreSQL"],
  "soft_skills": ["Communication", "Travail d'équipe", "Autonomie", "Résolution de problèmes"],
  "email": "jean.dupont@example.com",
  "telephone": "06 12 34 56 78",
  "adresse": "123 rue de Paris, 75001 Paris",
  "formations": [
    {
      "diplome": "Master Informatique",
      "etablissement": "Université Pierre et Marie Curie",
      "annee": 2018
    },
    {
      "diplome": "Licence Informatique",
      "etablissement": "Université Pierre et Marie Curie",
      "annee": 2016
    }
  ],
  "experiences": [
    {
      "poste": "Développeur Full Stack",
      "entreprise": "TechCorp",
      "debut": "2019-01",
      "fin": "2024-04",
      "description": "Développement d'applications web avec Django et React"
    },
    {
      "poste": "Développeur Junior",
      "entreprise": "StartInnov",
      "debut": "2018-03",
      "fin": "2018-12",
      "description": "Développement Python et Django"
    }
  ],
  "langues": [
    {
      "langue": "Français",
      "niveau": "Natif"
    },
    {
      "langue": "Anglais",
      "niveau": "Courant"
    },
    {
      "langue": "Espagnol",
      "niveau": "Intermédiaire"
    }
  ]
}
